env_bar/__init__.py
env_bar/apps.py
env_bar/middleware.py
env_bar/settings.py
env_bar/static/env_bar/css/bar.css
env_bar/templates/env_bar/bar.html
django_env_bar-0.0.4.dist-info/LICENSE
django_env_bar-0.0.4.dist-info/METADATA
django_env_bar-0.0.4.dist-info/WHEEL
django_env_bar-0.0.4.dist-info/top_level.txt
django_env_bar-0.0.4.dist-info/RECORD
